[{"name":"Afrikaans","code":"af"},{"name":"Albansk","code":"sq"},{"name":"Arabisk","code":"ar"},{"name":"Bulgarsk","code":"bg"},{"name":"Hviderussisk","code":"be"},{"name":"Catalansk","code":"ca"},{"name":"Kinesisk","code":"zh"},{"name":"Kroatisk","code":"hr"},{"name":"Tjekkisk","code":"cs"},{"name":"Danske","code":"da"},{"name":"Hollandsk","code":"nl"},{"name":"English","code":"en"},{"name":"Estisk","code":"et"},{"name":"Finsk","code":"fi"},{"name":"Fransk","code":"fr"},{"name":"Galiciske","code":"gl"},{"name":"Tysk","code":"de"},{"name":"Gr¾sk","code":"el"},{"name":"Hebraisk","code":"he"},{"name":"Hindi","code":"hi"},{"name":"Ungarske","code":"hu"},{"name":"Islandsk","code":"is"},{"name":"Indonesisk","code":"id"},{"name":"Irske","code":"ga"},{"name":"Italiensk","code":"it"},{"name":"Japansk","code":"ja"},{"name":"Koreansk","code":"ko"},{"name":"Lettisk","code":"lv"},{"name":"Litauisk","code":"lt"},{"name":"Makedonsk","code":"mk"},{"name":"Malay","code":"ms"},{"name":"Maltesiske","code":"mt"},{"name":"Norwegian","code":"no"},{"name":"Persisk","code":"fa"},{"name":"Polsk","code":"pl"},{"name":"Portugisisk","code":"pt"},{"name":"Rum¾nsk","code":"ro"},{"name":"Russisk","code":"ru"},{"name":"Serbisk","code":"sr"},{"name":"Slovakiske","code":"sk"},{"name":"Slovenske","code":"sl"},{"name":"Spansk","code":"es"},{"name":"Swahili","code":"sw"},{"name":"Thai","code":"th"},{"name":"Tyrkisk","code":"tr"},{"name":"Ukrainske","code":"uk"},{"name":"Vietnamesiske","code":"vi"},{"name":"Welch","code":"cy"},{"name":"Jiddisch","code":"yi"}]